AUTHORS.rst
LICENSE
MANIFEST.in
README.rst
setup.py
demo/__init__.py
demo/manage.py
demo/app/__init__.py
demo/app/models.py
demo/app/views.py
demo/app/migrations/0001_initial.py
demo/app/migrations/__init__.py
demo/project/__init__.py
demo/project/settings.py
demo/project/settings_test.py
demo/project/urls.py
demo/project/wsgi.py
django_yandex_kassa.egg-info/PKG-INFO
django_yandex_kassa.egg-info/SOURCES.txt
django_yandex_kassa.egg-info/dependency_links.txt
django_yandex_kassa.egg-info/requires.txt
django_yandex_kassa.egg-info/top_level.txt
yandex_kassa/__init__.py
yandex_kassa/admin.py
yandex_kassa/conf.py
yandex_kassa/forms.py
yandex_kassa/loggers.py
yandex_kassa/models.py
yandex_kassa/signals.py
yandex_kassa/urls.py
yandex_kassa/utils.py
yandex_kassa/views.py
yandex_kassa/migrations/0001_initial.py
yandex_kassa/migrations/0002_auto_20151111_1053.py
yandex_kassa/migrations/0003_auto_20151116_1530.py
yandex_kassa/migrations/0004_auto_20151209_0940.py
yandex_kassa/migrations/0005_auto_20160109_0638.py
yandex_kassa/migrations/0006_auto_20170920_0315.py
yandex_kassa/migrations/__init__.py
yandex_kassa/templates/yandex_kassa/fail_page.html
yandex_kassa/templates/yandex_kassa/success_page.html
yandex_kassa/tests/__init__.py
yandex_kassa/tests/base_test.py
yandex_kassa/tests/test_forms.py
yandex_kassa/tests/test_notification.py