Metadata-Version: 1.1
Name: django-yandex-kassa
Version: 0.9.14
Summary: Integrating django project with yandex-kassa
Home-page: https://github.com/DrMartiner/django-yandex-kassa
Author: Alexei Kuzmin
Author-email: DrMartiner@GMail.Com
License: MIT
Keywords: django,yandex,money,kassa,payment,pay,payment,ecommerce,shop,cart
Platform: UNKNOWN
Classifier: Environment :: Web Environment
Classifier: Framework :: Django
Classifier: Intended Audience :: Developers
Classifier: License :: OSI Approved :: MIT License
Classifier: Operating System :: OS Independent
Classifier: Programming Language :: Python
Classifier: Programming Language :: Python :: 2.6
Classifier: Programming Language :: Python :: 2.7
Classifier: Topic :: Internet :: WWW/HTTP
Classifier: Topic :: Internet :: WWW/HTTP :: Dynamic Content
